managesieve3.py
managesieve3-1.1.dist-info/DESCRIPTION.rst
managesieve3-1.1.dist-info/METADATA
managesieve3-1.1.dist-info/RECORD
managesieve3-1.1.dist-info/WHEEL
managesieve3-1.1.dist-info/metadata.json
managesieve3-1.1.dist-info/top_level.txt
