Metadata-Version: 2.0
Name: managesieve3
Version: 1.1
Summary: Implements an RFC-5804 Manage Sieve client.
Home-page: https://bitbucket.org/ericvsmith/managesieve3
Author: Eric V. Smith
Author-email: eric@trueblade.com
License: Apache License Version 2.0
Platform: UNKNOWN
Classifier: Development Status :: 5 - Production/Stable
Classifier: Intended Audience :: Developers
Classifier: License :: OSI Approved :: Apache Software License
Classifier: Topic :: Software Development :: Libraries :: Python Modules
Classifier: Programming Language :: Python :: 2.7
Classifier: Programming Language :: Python :: 3.3
Classifier: Programming Language :: Python :: 3.4
Classifier: Programming Language :: Python :: 3.5
